{
  "name": "bindfit",
  "title": "Bindfit",
  "profile": "datakit-algorithm",
  "code": "algorithm.py",
  "container": "datakits/bindfit",
  "signature": {
    "inputs": [
      {
        "name": "data",
        "title": "Input data",
        "description": "Input data",
        "type": "resource",
        "profile": "tabular-data-resource",
        "metaschemas": [
          "data",
          "dataAgg"
        ],
        "null": false,
        "default": {
          "resource": "data",
          "metaschema": "data"
        }
      },
      {
        "name": "method",
        "title": "Fit method",
        "description": "The optimisation method to use for fitting",
        "type": "string",
        "enum": [
          {
            "title": "Nelder-Mead",
            "value": "nelder-mead"
          },
          {
            "title": "L-BFGS-B",
            "value": "bfgs"
          }
        ],
        "null": false,
        "default": {
          "value": "nelder-mead"
        }
      },
      {
        "name": "model",
        "title": "Model",
        "description": "The model to fit to the data",
        "type": "string",
        "enum": [
          {
            "title": "NMR 1:1",
            "value": "nmr1to1"
          },
          {
            "title": "NMR 1:2",
            "value": "nmr1to2"
          },
          {
            "title": "NMR 2:1",
            "value": "nmr2to1"
          },
          {
            "title": "NMR Dimer",
            "value": "nmrdimer"
          },
          {
            "title": "NMR CoEK",
            "value": "nmrcoek"
          },
          {
            "title": "UV 1:1",
            "value": "uv1to1"
          },
          {
            "title": "UV 1:2",
            "value": "uv1to2"
          },
          {
            "title": "UV 2:1",
            "value": "uv2to1"
          },
          {
            "title": "UV Dimer",
            "value": "uvdimer"
          },
          {
            "title": "UV CoEK",
            "value": "uvcoek"
          }
        ],
        "null": false,
        "default": {
          "value": "nmr1to1"
        }
      },
      {
        "name": "inputParams",
        "title": "Input parameters",
        "description": "Fit parameter initial guesses and bounds",
        "type": "resource",
        "profile": "tabular-data-resource",
        "null": false,
        "default": {
          "resource": "inputParams"
        }
      },
      {
        "name": "subInitValues",
        "title": "Subtract initial values",
        "description": "If true, assumes the first data point is the chemical shift of the pure host and fits only the differences between pure host and complex(es)",
        "type": "boolean",
        "null": false,
        "default": {
          "value": true
        }
      },
      {
        "name": "dilutionCorrection",
        "title": "Dilution correction",
        "description": "If true, apply dilution correction to the data before fitting",
        "type": "boolean",
        "null": false,
        "default": {
          "value": false
        }
      },
      {
        "name": "flavour",
        "title": "Flavour",
        "description": "If true, apply dilution correction to the data before fitting",
        "type": "string",
        "enum": [
          {
            "title": "Add",
            "value": "add"
          },
          {
            "title": "Stat",
            "value": "stat"
          },
          {
            "title": "Non-coop",
            "value": "noncoop"
          }
        ],
        "null": true,
        "default": {
          "value": null,
          "disabled": true
        }
      }
    ],
    "outputs": [
      {
        "name": "outputParams",
        "title": "Output parameters",
        "description": "Optimised parameter values",
        "type": "resource",
        "profile": "tabular-data-resource",
        "null": false,
        "default": {
          "resource": "outputParams"
        }
      },
      {
        "name": "fit",
        "title": "Fit curve",
        "description": "Fit curve",
        "type": "resource",
        "profile": "tabular-data-resource",
        "null": true,
        "metaschemas": [
          "data",
          "dataAgg"
        ],
        "default": {
          "resource": "fit",
          "metaschema": "data"
        }
      },
      {
        "name": "residuals",
        "title": "Residuals",
        "description": "Fit residuals",
        "type": "resource",
        "profile": "tabular-data-resource",
        "null": true,
        "metaschemas": [
          "data",
          "dataAgg"
        ],
        "default": {
          "resource": "residuals",
          "metaschema": "data"
        }
      },
      {
        "name": "molefractions",
        "title": "Molefractions",
        "description": "Fit molefractions",
        "type": "resource",
        "profile": "tabular-data-resource",
        "null": true,
        "default": {
          "resource": "molefractions"
        }
      },
      {
        "name": "coefficients",
        "title": "Coefficients",
        "description": "Fit coefficients",
        "type": "resource",
        "profile": "tabular-data-resource",
        "null": true,
        "default": {
          "resource": "coefficients"
        }
      },
      {
        "name": "quality",
        "title": "Fit quality",
        "description": "Fit quality",
        "type": "resource",
        "profile": "tabular-data-resource",
        "null": true,
        "default": {
          "resource": "quality"
        }
      },
      {
        "name": "summary",
        "title": "Fit summary",
        "description": "Fit summary",
        "type": "resource",
        "profile": "tabular-data-resource",
        "null": true,
        "default": {
          "resource": "summary"
        }
      }
    ]
  }
}
